odoo/addons/l10n_us_gaap_mis_report/README.rst
odoo/addons/l10n_us_gaap_mis_report/__init__.py
odoo/addons/l10n_us_gaap_mis_report/__manifest__.py
odoo/addons/l10n_us_gaap_mis_report/data/mis_report_balance_sheet.xml
odoo/addons/l10n_us_gaap_mis_report/data/mis_report_income_statement.xml
odoo/addons/l10n_us_gaap_mis_report/data/mis_report_styles.xml
odoo/addons/l10n_us_gaap_mis_report/docs/l10n_us_gaap_balance_sheet.ods
odoo/addons/l10n_us_gaap_mis_report/docs/l10n_us_gaap_income_statement.ods
odoo/addons/l10n_us_gaap_mis_report/i18n/es.po
odoo/addons/l10n_us_gaap_mis_report/i18n/l10n_us_gaap_mis_report.pot
odoo/addons/l10n_us_gaap_mis_report/readme/CONFIGURE.rst
odoo/addons/l10n_us_gaap_mis_report/readme/CONTRIBUTORS.rst
odoo/addons/l10n_us_gaap_mis_report/readme/DESCRIPTION.rst
odoo/addons/l10n_us_gaap_mis_report/readme/INSTALL.rst
odoo/addons/l10n_us_gaap_mis_report/static/description/icon.png
odoo/addons/l10n_us_gaap_mis_report/static/description/index.html
odoo14_addon_l10n_us_gaap_mis_report-14.0.1.0.1.dev7.dist-info/METADATA
odoo14_addon_l10n_us_gaap_mis_report-14.0.1.0.1.dev7.dist-info/WHEEL
odoo14_addon_l10n_us_gaap_mis_report-14.0.1.0.1.dev7.dist-info/top_level.txt
odoo14_addon_l10n_us_gaap_mis_report-14.0.1.0.1.dev7.dist-info/RECORD
