Metadata-Version: 2.1
Name: odoo14-addon-l10n-us-gaap-mis-report
Version: 14.0.1.0.1.dev7
Summary: MIS Builder Templates for US Chart of Accounts
Home-page: https://github.com/OCA/l10n-usa
Author: ForgeFlow, Odoo Community Association (OCA)
Author-email: support@odoo-community.org
License: AGPL-3
Platform: UNKNOWN
Classifier: Programming Language :: Python
Classifier: Framework :: Odoo
Classifier: Framework :: Odoo :: 14.0
Classifier: License :: OSI Approved :: GNU Affero General Public License v3
Classifier: Development Status :: 5 - Production/Stable
Requires-Python: >=3.6
Requires-Dist: odoo14-addon-l10n-us-gaap
Requires-Dist: odoo14-addon-mis-builder
Requires-Dist: odoo <14.1dev,>=14.0a
